[
  {
  "id": "1",
  "name": "23 марта",
  "type": "FeatureCollection",
   "textTop":[
    {"name":"Встреча в аэропорту и трансфер до Лагеря"},
    {"name":"Заезд и расселение"},
    {"name":"Приветственный ужин и знакомства"},
    {"name":"Баня и бассейн"},
    {"name":"Бар и кальян или прогулка по вечернему Адлеру на электросамокатах и посиделки возле моря"}
   ],
   "textBottom":[
    {"name":"Форелевое хозяйство в Адлере"},
    {"name":"Чайные плантации в Хосте"},
    {"name":"Агурские водопады"},
    {"name":"Фотосессия"},
    {"name":"Тропа здоровья на Роза Хутор"},
    {"name":"Открытый аквапарк Газпром Галактика или Закрытый на высоте 540 Mountain Beach Ферма Экзархо"}
   ],
  "features": [
      {
        "id": "1",
        "name": "ул. 21 Линия, 1А",        
        "type": "Feature",
        "geometry": {
        "type": "Point",
        "coordinates": [
        51.777996,
        55.182142
        ]
        },
        "properties": {
        "balloonContentHeader": "",
        "balloonContentBody": "",
        "balloonContentFooter": ""
        },
        "nameCat": "23 марта"
      },
      {
        "id": "2",
        "name": "ул. Салмышская, д. 62",        
        "type": "Feature",
        "geometry": {
        "type": "Point",
        "coordinates": [
        51.767324, 
        55.282385
        ]
        },
        "properties": {
        "balloonContentHeader": "",
        "balloonContentBody": "",
        "balloonContentFooter": ""
        },
        "nameCat": "23 марта"
      },
      {
        "id": "3",
        "name": "пр. Дзержинского, д. 4, каб. 302",        
        "type": "Feature",
        "geometry": {
        "type": "Point",
        "coordinates": [
        51.721307, 
        55.149875
        ]
        },
        "properties": {
        "balloonContentHeader": "",
        "balloonContentBody": "",
        "balloonContentFooter": ""
        },
        "nameCat": "23 марта"
      }
    ]
  },
  {
  "id": "2",
  "name": "24 марта",
  "type": "FeatureCollection",
  "textTop":[
    {"name":"Встреча в аэропорту и трансфер до Лагеря!"},
    {"name":"Заезд и расселение!"},
    {"name":"Приветственный ужин и знакомства!"},
    {"name":"Баня и бассейн!"},
    {"name":"Бар и кальян или прогулка по вечернему Адлеру на электросамокатах и посиделки возле моря!"}
   ],
   "textBottom":[
    {"name":"Форелевое хозяйство в Адлере!"},
    {"name":"Чайные плантации в Хосте!"},
    {"name":"Агурские водопады!"},
    {"name":"Фотосессия!"},
    {"name":"Тропа здоровья на Роза Хутор!"},
    {"name":"Открытый аквапарк Газпром Галактика или Закрытый на высоте 540 Mountain Beach Ферма Экзархо!"}
   ],
  "features": [
      {
        "id": "4",
        "name": "улица Мусы Джалиля, 6",        
        "type": "Feature",
        "geometry": {
        "type": "Point",
        "coordinates": [
        51.763918, 
        55.073976
        ]
        },
        "properties": {
        "balloonContentHeader": "",
        "balloonContentBody": "",
        "balloonContentFooter": ""
        },
        "nameCat": "24 марта"
      },
      {
        "id": "5",
        "name": "улица Чичерина, 2",        
        "type": "Feature",
        "geometry": {
        "type": "Point",
        "coordinates": [
        51.756014, 
        55.092329
        ]
        },
        "properties": {
        "balloonContentHeader": "",
        "balloonContentBody": "",
        "balloonContentFooter": ""
        },
        "nameCat": "24 марта"
      },
      {
        "id": "6",
        "name": "Кондукторский переулок, 4",        
        "type": "Feature",
        "geometry": {
        "type": "Point",
        "coordinates": [
        51.770724, 
        55.075935
        ]
        },
        "properties": {
        "balloonContentHeader": "",
        "balloonContentBody": "",
        "balloonContentFooter": ""
        },
        "nameCat": "24 марта"
      }
    ]
  },
  {
  "id": "3",
  "name": "25 марта",
  "type": "FeatureCollection",
  "textTop":[
    {"name":"Встреча в аэропорту и трансфер до Лагеря3"},
    {"name":"Заезд и расселение3"},
    {"name":"Приветственный ужин и знакомства3"},
    {"name":"Баня и бассейн3"},
    {"name":"Бар и кальян или прогулка по вечернему Адлеру на электросамокатах и посиделки возле моря3"}
   ],
  "textBottom":[
    {"name":"Форелевое хозяйство в Адлере3"},
    {"name":"Чайные плантации в Хосте3"},
    {"name":"Агурские водопады3"},
    {"name":"Фотосессия!"},
    {"name":"Тропа здоровья на Роза Хутор3"},
    {"name":"Открытый аквапарк Газпром Галактика или Закрытый на высоте 540 Mountain Beach Ферма Экзархо3"}
   ],
  "features": [
      {
        "id": "7",
        "name": "улица Джангильдина",        
        "type": "Feature",
        "geometry": {
        "type": "Point",
        "coordinates": [
        51.831759,
        55.158831
        ]
        },
        "properties": {
        "balloonContentHeader": "",
        "balloonContentBody": "",
        "balloonContentFooter": ""
        },
        "nameCat": "25 марта"
      },
      {
        "id": "8",
        "name": "улица Юных Ленинцев",        
        "type": "Feature",
        "geometry": {
        "type": "Point",
        "coordinates": [
        51.837814, 
        55.142320
        ]
        },
        "properties": {
        "balloonContentHeader": "",
        "balloonContentBody": "",
        "balloonContentFooter": ""
        },
        "nameCat": "25 марта"
      },
      {
        "id": "9",
        "name": "улица Дружбы, 12/1",        
        "type": "Feature",
        "geometry": {
        "type": "Point",
        "coordinates": [
        51.834764, 
        55.143344
        ]
        },
        "properties": {
        "balloonContentHeader": "",
        "balloonContentBody": "",
        "balloonContentFooter": ""
        },
        "nameCat": "25 марта"
      }
    ]
  },
  {
  "id": "4",
  "name": "26 марта",
  "type": "FeatureCollection",
  "textTop":[
    {"name":"Встреча в аэропорту и трансфер до Лагеря4"},
    {"name":"Заезд и расселение4"},
    {"name":"Приветственный ужин и знакомства4"},
    {"name":"Баня и бассейн4"},
    {"name":"Бар и кальян или прогулка по вечернему Адлеру на электросамокатах и посиделки возле моря4"}
   ],
  "textBottom":[
    {"name":"Форелевое хозяйство в Адлере4"},
    {"name":"Чайные плантации в Хосте4"},
    {"name":"Агурские водопады4"},
    {"name":"Фотосессия4"},
    {"name":"Тропа здоровья на Роза Хутор4"},
    {"name":"Открытый аквапарк Газпром Галактика или Закрытый на высоте 540 Mountain Beach Ферма Экзархо4"}
   ],
  "features": [
      {
        "id": "10",
        "name": "Ташкентская улица, 28с1",        
        "type": "Feature",
        "geometry": {
        "type": "Point",
        "coordinates": [
        55.699162, 
        37.806084
        ]
        },
        "properties": {
        "balloonContentHeader": "",
        "balloonContentBody": "",
        "balloonContentFooter": ""
        },
        "nameCat": "26 марта"
      },
      {
        "id": "11",
        "name": "микрорайон 70-летия ВЛКСМ",        
        "type": "Feature",
        "geometry": {
        "type": "Point",
        "coordinates": [
        51.828486, 
        55.140892
        ]
        },
        "properties": {
        "balloonContentHeader": "",
        "balloonContentBody": "",
        "balloonContentFooter": ""
        },
        "nameCat": "26 марта"
      },
      {
        "id": "12",
        "name": "проспект Братьев Коростелёвых",        
        "type": "Feature",
        "geometry": {
        "type": "Point",
        "coordinates": [
        51.797640, 
        55.065918
        ]
        },
        "properties": {
        "balloonContentHeader": "",
        "balloonContentBody": "",
        "balloonContentFooter": ""
        },
        "nameCat": "26 марта"
      }
    ]
  },
  {
  "id": "5",
  "name": "27 марта",
  "type": "FeatureCollection",
  "textTop":[
    {"name":"Встреча в аэропорту и трансфер до Лагеря5"},
    {"name":"Заезд и расселение5"},
    {"name":"Приветственный ужин и знакомства5"},
    {"name":"Баня и бассейн5"},
    {"name":"Бар и кальян или прогулка по вечернему Адлеру на электросамокатах и посиделки возле моря5"}
   ],
  "textBottom":[
    {"name":"Форелевое хозяйство в Адлере5"},
    {"name":"Чайные плантации в Хосте5"},
    {"name":"Агурские водопады5"},
    {"name":"Фотосессия5"},
    {"name":"Тропа здоровья на Роза Хутор5"},
    {"name":"Открытый аквапарк Газпром Галактика или Закрытый на высоте 540 Mountain Beach Ферма Экзархо5"}
   ],
  "features": [
      {
        "id": "13",
        "name": "Невельская улица, 24",        
        "type": "Feature",
        "geometry": {
        "type": "Point",
        "coordinates": [
        51.785396, 
        55.108975
        ]
        },
        "properties": {
        "balloonContentHeader": "",
        "balloonContentBody": "",
        "balloonContentFooter": ""
        },
        "nameCat": "27 марта"
      },
      {
        "id": "14",
        "name": "Орская улица",        
        "type": "Feature",
        "geometry": {
        "type": "Point",
        "coordinates": [
        51.879120, 
        55.043721
        ]
        },
        "properties": {
        "balloonContentHeader": "",
        "balloonContentBody": "",
        "balloonContentFooter": ""
        },
        "nameCat": "27 марта"
      }
      
    ]
  },
  {
  "id": "6",
  "name": "28 марта",
  "type": "FeatureCollection",
  "textTop":[
    {"name":"Встреча в аэропорту и трансфер до Лагеря6"},
    {"name":"Заезд и расселение6"},
    {"name":"Приветственный ужин и знакомства6"},
    {"name":"Баня и бассейн6"},
    {"name":"Бар и кальян или прогулка по вечернему Адлеру на электросамокатах и посиделки возле моря6"}
   ],
  "textBottom":[
    {"name":"Форелевое хозяйство в Адлере6"},
    {"name":"Чайные плантации в Хосте6"},
    {"name":"Агурские водопады6"},
    {"name":"Фотосессия6"},
    {"name":"Тропа здоровья на Роза Хутор6"},
    {"name":"Открытый аквапарк Газпром Галактика или Закрытый на высоте 540 Mountain Beach Ферма Экзархо6"}
   ],
  "features": [
      {
        "id": "15",
        "name": "Невельская улица, 24",        
        "type": "Feature",
        "geometry": {
        "type": "Point",
        "coordinates": [
        51.785396, 
        55.108975
        ]
        },
        "properties": {
        "balloonContentHeader": "",
        "balloonContentBody": "",
        "balloonContentFooter": ""
        },
        "nameCat": "28 марта"
      },
      {
        "id": "16",
        "name": "улица Карла Маркса",        
        "type": "Feature",
        "geometry": {
        "type": "Point",
        "coordinates": [
        51.768717, 
        55.134397
        ]
        },
        "properties": {
        "balloonContentHeader": "",
        "balloonContentBody": "",
        "balloonContentFooter": ""
        },
        "nameCat": "28 марта"
      }
      
    ]
  },
  {
  "id": "7",
  "name": "29 марта",
  "type": "FeatureCollection",
  "textTop":[
    {"name":"Встреча в аэропорту и трансфер до Лагеря7"},
    {"name":"Заезд и расселение7"},
    {"name":"Приветственный ужин и знакомства7"},
    {"name":"Баня и бассейн7"},
    {"name":"Бар и кальян или прогулка по вечернему Адлеру на электросамокатах и посиделки возле моря7"}
   ],
  "textBottom":[
    {"name":"Форелевое хозяйство в Адлере7"},
    {"name":"Чайные плантации в Хосте7"},
    {"name":"Агурские водопады7"},
    {"name":"Фотосессия7"},
    {"name":"Тропа здоровья на Роза Хутор7"},
    {"name":"Открытый аквапарк Газпром Галактика или Закрытый на высоте 540 Mountain Beach Ферма Экзархо7"}
   ],
  "features": [
      {
        "id": "17",
        "name": "СНТ Медик",        
        "type": "Feature",
        "geometry": {
        "type": "Point",
        "coordinates": [
        51.727817, 
        55.123779
        ]
        },
        "properties": {
        "balloonContentHeader": "",
        "balloonContentBody": "",
        "balloonContentFooter": ""
        },
        "nameCat": "29 марта"
      },
      {
        "id": "18",
        "name": "Алтайская улица, 4",        
        "type": "Feature",
        "geometry": {
        "type": "Point",
        "coordinates": [
        51.776910, 
        55.165685
        ]
        },
        "properties": {
        "balloonContentHeader": "",
        "balloonContentBody": "",
        "balloonContentFooter": ""
        },
        "nameCat": "29 марта"
      }
      
    ]
  }

]